AUTHORS
CHANGES.rst
LICENSE
MANIFEST.in
README.rst
setup.py
django_scss/__init__.py
django_scss/cache.py
django_scss/devmode.py
django_scss/finders.py
django_scss/models.py
django_scss/settings.py
django_scss/storage.py
django_scss/utils.py
django_scss.egg-info/PKG-INFO
django_scss.egg-info/SOURCES.txt
django_scss.egg-info/dependency_links.txt
django_scss.egg-info/top_level.txt
django_scss/templatetags/__init__.py
django_scss/templatetags/scss.py
django_scss/tests/__init__.py
django_scss/tests/django_settings.py
django_scss/tests/tests.py