Metadata-Version: 1.0
Name: django-scss
Version: 0.6.1
Summary: Django template tags to compile SCSS into CSS
Home-page: https://github.com/andreyfedoseev/django-scss
Author: Andrey Fedoseev
Author-email: andrey.fedoseev@gmail.com
License: UNKNOWN
Keywords: scss,css
Platform: UNKNOWN
Classifier: Development Status :: 4 - Beta
Classifier: Framework :: Django
Classifier: Intended Audience :: Developers
Classifier: License :: OSI Approved :: BSD License
Classifier: Operating System :: OS Independent
Classifier: Programming Language :: Python
Classifier: Topic :: Internet :: WWW/HTTP
